iglu_py/__init__.py
iglu_py/bridge.py
iglu_py/df.py
iglu_py/iglu_4.1.7.tar.gz
iglu_py/metrics.py
iglu_py/data/example_data_1_subject.csv
iglu_py/data/example_data_5_subject.csv
iglu_py/data/example_data_hall.csv
iglu_py/data/example_meals_hall.csv
iglu_py-1.1.1.dist-info/METADATA
iglu_py-1.1.1.dist-info/WHEEL
iglu_py-1.1.1.dist-info/top_level.txt
iglu_py-1.1.1.dist-info/RECORD
