Metadata-Version: 2.1
Name: iglu-py
Version: 1.1.1
Summary: Python wrapper of R package `iglu` for continuous glucose monitoring data analysis. Wraps the R functions, thus making them accessible in Python.
Author: Nathaniel J. Fernandes, Lizzie Chun, Irina Gaynanova
Author-email: njfernandes24@tamu.edu, lizzie_chun1@tamu.edu, irinagn@umich.edu
Keywords: iglu,Continuous Glucose Monitoring analysis software,diabetes
Requires-Python: >=3.8.0
Requires-Dist: rpy2 >=3.5.13
Requires-Dist: pandas >=2.0.0
